{"protounitsounddef":{"#text":"","protounit":{"@name":"deLegionDragoon","#text":"","soundtype":[{"@name":"Select","#text":"","techlogic":{"#text":"","choice":[{"@name":"none","#text":"","soundset":{"@name":"FrenchDragoonSelect","#text":""}},{"@name":"DEHCREVBuenosAires","#text":"","soundset":{"@name":"SpanishDragoonSelect","#text":""}}]}},{"@name":"Grunt","#text":"","soundset":{"@name":"CavalryGrunt","#text":""}},{"@name":"Death","#text":"","soundset":{"@name":"GenericMaleDeath","#text":""}},{"@name":"Acknowledge","#text":"","targetlogic":{"#text":"","choice":[{"@name":"default","#text":"","techlogic":{"#text":"","choice":[{"@name":"none","#text":"","soundset":{"@name":"FrenchDragoonAcknowledge","#text":""}},{"@name":"DEHCREVBuenosAires","#text":"","soundset":{"@name":"SpanishDragoonAcknowledge","#text":""}}]}},{"@name":"enemy","#text":"","techlogic":{"#text":"","choice":[{"@name":"none","#text":"","soundset":{"@name":"FrenchDragoonAttack","#text":""}},{"@name":"DEHCREVBuenosAires","#text":"","soundset":{"@name":"SpanishDragoonAttack","#text":""}}]}}]}},{"@name":"Creation","#text":"","soundset":{"@name":"MilitaryBirth","#text":""}}]}}}