{"protounitsounddef":{"#text":"","protounit":{"@name":"deSaloonHajduk","#text":"","soundtype":[{"@name":"Select","#text":"","soundset":{"@name":"RomanianMilitarySelect","#text":""}},{"@name":"Grunt","#text":"","soundset":{"@name":"GenericMaleGrunt","#text":""}},{"@name":"Death","#text":"","soundset":{"@name":"GenericMaleDeath","#text":""}},{"@name":"Creation","#text":"","soundset":{"@name":"MilitaryBirth","#text":""}},{"@name":"Acknowledge","#text":"","targetlogic":{"#text":"","choice":[{"@name":"default","#text":"","soundset":{"@name":"RomanianMilitaryAcknowledge","#text":""}},{"@name":"enemy","#text":"","soundset":{"@name":"RomanianMilitaryAttack","#text":""}}]}}]}}}