{"protounitsounddef":{"#text":"","protounit":{"@name":"Outlaw","#text":"","soundtype":[{"@name":"Select","#text":"","soundset":{"@name":"NativeTempSelect","#text":""}},{"@name":"Grunt","#text":"","soundset":{"@name":"GenericMale4Grunt","#text":""}},{"@name":"Death","#text":"","soundset":{"@name":"GenericMale4Death","#text":""}},{"@name":"Creation","#text":"","soundset":{"@name":"NativeBirth","#text":""}},{"@name":"Acknowledge","#text":"","targetlogic":{"#text":"","choice":[{"@name":"default","#text":"","soundset":{"@name":"NativeTempAcknowledge","#text":""}},{"@name":"enemy","#text":"","soundset":{"@name":"NativeTempAttack","#text":""}}]}}]}}}