{"protounitsounddef":{"#text":"","protounit":{"@name":"SPCLizzieFlagship","#text":"","soundtype":[{"@name":"Select","#text":"","soundset":{"@name":"ElizabetRamseySelect","#text":""}},{"@name":"Death","#text":"","soundset":{"@name":"ShipDeath","#text":""}},{"@name":"Creation","#text":"","soundset":{"@name":"ShipBirth","#text":""}},{"@name":"Acknowledge","#text":"","soundset":{"@name":"ElizabetRamseyFlagshipAcknowledge","#text":""}},{"@name":"Exists","#text":"","soundset":{"@name":"AmbienceShip","#text":""}}]}}}