{"tactics":{"#text":"","action":[{"#text":"","name":{"@stringid":"112252","#text":"AreaHeal"},"type":"AutoRangedModify","maxrange":"20","modifyabstracttype":"LogicalTypeHealed","persistent":"1","modifytype":"HealRate","modifyamount":"10","modifytargetlimit":"50","restricttoidleunits":"1","modelattachment":"effects\\areaheal.xml","modelattachmentbone":"bonethatdoesntexist"},{"#text":"","name":{"@stringid":"69155","#text":"Heal"},"active":"0","type":"Heal","maxrange":"20","rate":{"@type":"LogicalTypeHealed","#text":"20.0 "},"anim":"Heal"},{"#text":"","name":{"@stringid":"43295","#text":"AutoGatherFood"},"type":"AutoGather","active":"0","persistent":"1"}],"tactic":{"#text":"Normal","action":["AutoGatherFood","AreaHeal"]}}}