{"tactics":{"#text":"","action":[{"#text":"","name":{"@stringid":"38129","#text":"StaggerRangedAttack"},"type":"Attack","attackaction":"1","rangedlogic":"1","anim":"Attack_ranged","idleanim":"Idle","reloadanim":"Attack_ranged_reload","maxheight":"0","accuracy":"1.0","aimbonus":"0","maxspread":"5","spreadfactor":"0.25","trackrating":"120","unintentionaldamagemultiplier":"0.7","projectile":"InvisibleProjectile","impacteffect":"effects\\impacts\\gun","minrange":"2","rate":{"@type":"Unit","#text":"1.0"},"instantballistics":"1","perfectaccuracy":"1"},{"#text":"","name":{"@stringid":"42873","#text":"GuardianRangedAttack"},"type":"Attack","attackaction":"1","rangedlogic":"1","anim":"Attack_ranged","idleanim":"Idle","reloadanim":"Attack_ranged_reload","maxheight":"0","accuracy":"1.0","aimbonus":"0","maxspread":"5","spreadfactor":"0.25","trackrating":"120","unintentionaldamagemultiplier":"0.7","projectile":"InvisibleProjectile","impacteffect":"effects\\impacts\\gun","minrange":"2","rate":{"@type":"Guardian","#text":"1.0"},"instantballistics":"1","perfectaccuracy":"1","hidefromstats":"1"},{"#text":"","name":{"@stringid":"38135","#text":"MeleeHandAttack"},"type":"Attack","maxrange":"1.75","rate":{"@type":"Unit","#text":"1.0"},"attackaction":"1","handlogic":"1","speedboost":"1","anim":"Attack_melee","idleanim":"Idle_melee","impacteffect":"effects\\impacts\\melee","damage":"6.5","rof":"1.0","targetspeedboost":"1"},{"#text":"","name":{"@stringid":"42873","#text":"GuardianAttack"},"type":"Attack","maxrange":"1.75","rate":{"@type":"Guardian","#text":"1.0"},"attackaction":"1","handlogic":"1","speedboost":"1","anim":"Attack_melee","idleanim":"Idle_melee","impacteffect":"effects\\impacts\\melee","damage":"6.5","rof":"1.0","targetspeedboost":"1","hidefromstats":"1"},{"#text":"","name":{"@stringid":"38142","#text":"TrampleHandAttack"},"type":"Attack","maxrange":"1.75","rate":{"@type":"Unit","#text":"1.0"},"attackaction":"1","handlogic":"1","speedboost":"1","anim":"Attack_trample","idleanim":"Idle_melee","impacteffect":"effects\\impacts\\melee","damage":"6.5","rof":"1.0","targetspeedboost":"1","basedamagecap":"1"},{"#text":"","name":{"@stringid":"38136","#text":"DefendRangedAttack"},"type":"Attack","attackaction":"1","rangedlogic":"1","anim":"Attack_ranged","reloadanim":"Attack_ranged_reload","idleanim":"Idle","maxheight":"0","accuracy":"1.0","aimbonus":"0","maxspread":"5","spreadfactor":"0.25","trackrating":"120","unintentionaldamagemultiplier":"1.0","projectile":"InvisibleProjectile","impacteffect":"effects\\impacts\\gun","minrange":"2","rate":{"@type":"Unit","#text":"1.0"},"instantballistics":"1","perfectaccuracy":"1"},{"#text":"","name":{"@stringid":"38118","#text":"BuildingAttack"},"type":"Attack","rangedlogic":"1","maxrange":"6","rate":{"@type":"Building","#text":"1.0"},"attackaction":"1","speedboost":"1","anim":"Raze_attack","idleanim":"Raze_idle","projectile":"TorchProjectile","impacteffect":"effects\\impacts\\torch"},{"#text":"","name":{"@stringid":"69148","#text":"DelayedTransform"},"type":"DelayedTransform","anim":"Dismount","animationrate":"0.46875","modifyprotoid":"deNatMountedInfantry"}],"tactic":[{"#text":"Stagger","action":[{"@priority":"75","#text":"BuildingAttack"},{"@priority":"100","#text":"GuardianRangedAttack"},{"@priority":"95","#text":"StaggerRangedAttack"},{"@priority":"90","#text":"MeleeHandAttack"}],"attacktype":"LogicalTypeRangedUnitsAttack","autoattacktype":"LogicalTypeRangedUnitsAutoAttack","attackresponsetype":"LogicalTypeRangedUnitsAttack","runaway":"0","autoretarget":"1","idleanim":"Idle","boredanim":"Bored","deathanim":"Death_by_range","walkanim":"Walk","joganim":"Jog","runanim":"Run"},{"#text":"Defend","action":[{"@priority":"75","#text":"BuildingAttack"},{"@priority":"100","#text":"GuardianRangedAttack"},{"@priority":"95","#text":"DefendRangedAttack"},{"@priority":"90","#text":"MeleeHandAttack"}],"attacktype":"LogicalTypeRangedUnitsAttack","autoattacktype":"LogicalTypeRangedUnitsAutoAttack","attackresponsetype":"LogicalTypeRangedUnitsAttack","runaway":"1","autoretarget":"1","idleanim":"Idle","boredanim":"Bored","deathanim":"Death_by_range","walkanim":"Walk","joganim":"Jog","runanim":"Run"},{"#text":"Trample","speedmodifier":"0.5","action":[{"@priority":"100","#text":"BuildingAttack"},{"@priority":"75","#text":"GuardianAttack"},{"@priority":"25","#text":"TrampleHandAttack"}],"attacktype":"LogicalTypeHandUnitsAttack","autoattacktype":"LogicalTypeHandUnitsAutoAttack","attackresponsetype":"LogicalTypeHandUnitsAttack","runaway":"0","autoretarget":"1","idleanim":"Idle_melee","boredanim":"Bored_melee","deathanim":"Death_by_melee","walkanim":"Highstep","joganim":"Jog_melee","runanim":"Run_melee"},{"#text":"Melee","action":[{"@priority":"75","#text":"BuildingAttack"},{"@priority":"100","#text":"MeleeHandAttack"}],"attacktype":"LogicalTypeRangedUnitsAttack","autoattacktype":"LogicalTypeRangedUnitsAutoAttack","attackresponsetype":"LogicalTypeRangedUnitsAttack","runaway":"0","autoretarget":"1","idleanim":"Idle_melee","boredanim":"Bored_melee","deathanim":"Death_by_melee","walkanim":"Walk_melee","joganim":"Jog_melee","runanim":"Run_melee"},{"#text":"StandGround","action":[{"@priority":"75","#text":"BuildingAttack"},{"@priority":"100","#text":"GuardianRangedAttack"},{"@priority":"95","#text":"DefendRangedAttack"},{"@priority":"90","#text":"MeleeHandAttack"}],"attacktype":"LogicalTypeRangedUnitsAttack","autoattacktype":"LogicalTypeRangedUnitsAutoAttack","attackresponsetype":"LogicalTypeRangedUnitsAttack","runaway":"1","autoretarget":"1","idleanim":"Idle","boredanim":"Bored","deathanim":"Death_by_range","walkanim":"Walk","joganim":"Jog","runanim":"Run"}]}}