{"economymode":{"#text":"","globalsettings":{"#text":"","tech":"DEEconomyMode","norushtime":"10","militarypopulationcap":"25","unitregen":{"#text":"","unittype":"Military","halflife":"30","excludeunittypes":{"#text":"","unittype":["Hero","AbstractWagon"]}}},"gamemodetypes":{"#text":"","gamemodetype":[{"@type":"timed","@name":"Timeout 10 mins","@nameid":"55533","#text":"","gametime":"10"},{"@type":"timed","@name":"Timeout 20 mins","@nameid":"55534","#text":"","gametime":"20"},{"@type":"timed","@name":"Timeout 30 mins","@nameid":"55535","#text":"","gametime":"30"},{"@type":"timed","@name":"Timeout 40 mins","@nameid":"55536","#text":"","gametime":"40"},{"@type":"timed","@name":"Timeout 60 mins","@nameid":"55537","#text":"","gametime":"60"},{"@type":"score","@name":"Score Limit 10k","@nameid":"55538","#text":"","scorelimit":"10000"},{"@type":"score","@name":"Score Limit 30k","@nameid":"55539","#text":"","scorelimit":"30000"},{"@type":"score","@name":"Score Limit 100k","@nameid":"55540","#text":"","scorelimit":"100000"},{"@type":"score","@name":"Score Limit 250k","@nameid":"55632","#text":"","scorelimit":"250000"},{"@type":"score","@name":"Score Limit 500k","@nameid":"55633","#text":"","scorelimit":"500000"},{"@type":"score","@name":"Score Limit 750k","@nameid":"55634","#text":"","scorelimit":"750000"}]},"scoring":{"#text":"","scoremode":"Default","scoremultiplier":{"@civ":"default","#text":"","food":"1","wood":"1","gold":"1","trade":"1","influence":"1","score":"1","ecobonus":"1"},"aiscoremultiplier":[{"@difficulty":"0","#text":"1"},{"@difficulty":"1","#text":"1"},{"@difficulty":"2","#text":"1"},{"@difficulty":"3","#text":"1"},{"@difficulty":"4","#text":"1"},{"@difficulty":"5","#text":"1"}]},"economyvictory":{"#text":"","scoreadvantage":"10000","victorytime":"300","firstwarningtime":"150","finalwarningtime":"60"},"challenges":{"#text":"","placestrings":{"#text":"","place":[{"@place":"1st","#text":"55500"},{"@place":"2nd","#text":"55501"},{"@place":"3rd","#text":"55502"}]},"challenge":[{"@name":"Tiered Food Gathering","#text":"","level":[{"@place":"1st","@type":"GatherFood","@amount":"800","@time":"3","@score":"1000","@stringid":"49945","@shortstringid":"55522","#text":""},{"@place":"2nd","@type":"GatherFood","@amount":"800","@time":"5","@score":"500","@stringid":"49945","@shortstringid":"55522","#text":""},{"@place":"3rd","@type":"GatherFood","@amount":"800","@time":"7","@score":"250","@stringid":"49945","@shortstringid":"55522","#text":""}]},{"@name":"Tiered Wood Gathering","#text":"","level":[{"@place":"1st","@type":"GatherWood","@amount":"1500","@time":"7","@score":"2000","@stringid":"49946","@shortstringid":"55523","#text":""},{"@place":"2nd","@type":"GatherWood","@amount":"1500","@time":"9","@score":"1000","@stringid":"49946","@shortstringid":"55523","#text":""},{"@place":"3rd","@type":"GatherWood","@amount":"1500","@time":"11","@score":"500","@stringid":"49946","@shortstringid":"55523","#text":""}]},{"@name":"Tiered Coin Gathering","#text":"","level":[{"@place":"1st","@type":"GatherGold","@amount":"2000","@time":"11","@score":"2500","@stringid":"49947","@shortstringid":"55524","#text":""},{"@place":"2nd","@type":"GatherGold","@amount":"2000","@time":"13","@score":"2000","@stringid":"49947","@shortstringid":"55524","#text":""},{"@place":"3rd","@type":"GatherGold","@amount":"2000","@time":"15","@score":"1000","@stringid":"49947","@shortstringid":"55524","#text":""}]},{"@name":"Tiered Population Reached","#text":"","level":[{"@place":"1st","@type":"Population","@amount":"50","@time":"14","@score":"3000","@stringid":"49948","@shortstringid":"55525","#text":""},{"@place":"2nd","@type":"Population","@amount":"50","@time":"16","@score":"2000","@stringid":"49948","@shortstringid":"55525","#text":""},{"@place":"3rd","@type":"Population","@amount":"50","@time":"18","@score":"1000","@stringid":"49948","@shortstringid":"55525","#text":""}]},{"@name":"Commerce Age","#text":"","level":{"@place":"1st","@type":"Age","@amount":"1","@score":"500","@stringid":"55595","@shortstringid":"55602","@substring1id":"55596","@perplayer":"true","#text":""}},{"@name":"Fortress Age","#text":"","level":{"@place":"1st","@type":"Age","@amount":"2","@score":"1000","@stringid":"55595","@shortstringid":"55602","@substring1id":"55597","@perplayer":"true","#text":""}},{"@name":"Industrial Age","#text":"","level":{"@place":"1st","@type":"Age","@amount":"3","@score":"1500","@stringid":"55595","@shortstringid":"55602","@substring1id":"55598","@perplayer":"true","#text":""}},{"@name":"Imperial Age","#text":"","level":{"@place":"1st","@type":"Age","@amount":"4","@score":"2000","@stringid":"55595","@shortstringid":"55602","@substring1id":"55599","@perplayer":"true","#text":""}},{"@name":"Revolt","#text":"","level":{"@place":"1st","@type":"Revolt","@amount":"1","@score":"250","@stringid":"55603","@shortstringid":"55604","@perplayer":"true","#text":""}},{"@name":"Revolt2","#text":"","level":{"@place":"2nd","@type":"Revolt","@amount":"2","@score":"500","@stringid":"55689","@shortstringid":"55604","@perplayer":"true","#text":""}},{"@name":"Homecity Shipment1","#text":"","level":{"@place":"1st","@type":"Shipment","@amount":"5","@score":"500","@stringid":"55624","@perplayer":"true","@shortstringid":"55625","#text":""}},{"@name":"Homecity Shipment2","#text":"","level":{"@place":"1st","@type":"Shipment","@amount":"10","@score":"1000","@stringid":"55624","@perplayer":"true","@shortstringid":"55625","#text":""}},{"@name":"Homecity Shipment3","#text":"","level":{"@place":"1st","@type":"Shipment","@amount":"15","@score":"1500","@stringid":"55624","@perplayer":"true","@shortstringid":"55625","#text":""}},{"@name":"Homecity Shipment4","#text":"","level":{"@place":"1st","@type":"Shipment","@amount":"20","@score":"2000","@stringid":"55624","@perplayer":"true","@shortstringid":"55625","#text":""}},{"@name":"Research Improvements","#text":"","level":{"@place":"1st","@type":"Research","@amount":"10","@score":"2000","@stringid":"55626","@perplayer":"true","@shortstringid":"55627","#text":""}}]},"ecopackages":{"#text":"","maxmultiple":"5","purchasetime":"30","minbonus":"20","maxbonus":"100","bonusreduction":[{"@multiple":"1","#text":"6"},{"@multiple":"2","#text":"11"},{"@multiple":"3","#text":"15"},{"@multiple":"4","#text":"18"},{"@multiple":"5","#text":"20"}],"bonusregenrate":"0.2","agemultiplier":[{"@age":"2","#text":"1"},{"@age":"3","#text":"1.5"},{"@age":"4","#text":"2"},{"@age":"5","#text":"4"}],"ecopackage":[{"@name":"FoodWood","@nameid":"55637","#text":"","icon":"resources\\images\\economy\\eco_packages_fw.png","cost":{"#text":"","food":"60","wood":"40"},"bonuspoints":[{"@age":"2","#text":"200"},{"@age":"3","#text":"170"},{"@age":"4","#text":"140"},{"@age":"5","#text":"85"}],"purchasedstringid":"55521"},{"@name":"FoodGold","@nameid":"55638","#text":"","icon":"resources\\images\\economy\\eco_packages_fc.png","cost":{"#text":"","food":"40","gold":"60"},"bonuspoints":[{"@age":"2","#text":"200"},{"@age":"3","#text":"170"},{"@age":"4","#text":"140"},{"@age":"5","#text":"85"}],"purchasedstringid":"55521"},{"@name":"WoodGold","@nameid":"55639","#text":"","icon":"resources\\images\\economy\\eco_packages_wc.png","cost":{"#text":"","wood":"40","gold":"40"},"bonuspoints":[{"@age":"2","#text":"220"},{"@age":"3","#text":"188"},{"@age":"4","#text":"155"},{"@age":"5","#text":"94"}],"purchasedstringid":"55521"},{"@name":"Export","@nameid":"55641","#text":"","icon":"resources\\images\\economy\\eco_packages_e.png","cost":{"#text":"","trade":"60"},"bonuspoints":[{"@age":"2","#text":"200"},{"@age":"3","#text":"170"},{"@age":"4","#text":"140"},{"@age":"5","#text":"85"}],"purchasedstringid":"55521"},{"@name":"Influence","@nameid":"55640","#text":"","icon":"resources\\images\\economy\\eco_packages_i.png","cost":{"#text":"","influence":"100"},"bonuspoints":[{"@age":"2","#text":"200"},{"@age":"3","#text":"170"},{"@age":"4","#text":"140"},{"@age":"5","#text":"85"}],"purchasedstringid":"55521"}]}}}