{"layout":{"#text":"","gadget":{"@name":"homeCityDeckButtons","@type":"gadget","@size1024":"220 638 343 768","@transparent":"","@tilebackgroundvert":"","@tilebackgroundhoriz":"","@background":"ui\\home_city\\HC_UI_background_wood","@hidden":"","@z":"50","#text":"","gadget":[{"@name":"homeCityCardPanel-DeckLabel","@type":"formatText","@size1024":"234 642 332 664","@textcolor":"255 255 255","@textcenterhoriz":"","@textcentervert":"","@textfont":"AgeText","@textfontsize":"12","@z":"30","#text":"Decks"},{"@name":"homeCityDeckButtons-SelectButton","@type":"stateButton","@size1024":"231 699 336 731","@bevelbutton":"","@z":"51","@statebuttonuseinternalstates":"","@textfont":"PregameButtons","@textfontsize":"18","@textcolor":"255 255 255","@textcenterhoriz":"","@textcentervert":"","@texturecoords":"0 0 0.6328125 1","@mouseovertext":"$$41537$$","@sound":"UI_DefaultPregameClickSet","#text":"Select","command":"gadgetReal(\"UIHCDeckPicker\")","stateentry":[{"@background":"ui\\core_ui\\button_large_normal","#text":""},{"@background":"ui\\core_ui\\button_large_clicked","#text":""},{"@background":"ui\\core_ui\\button_large_high","#text":""},{"@background":"ui\\core_ui\\button_large_disable","#text":""}]},{"@name":"homeCityDeckButtons-CreateButton","@type":"stateButton","@size1024":"231 666 336 700","@bevelbutton":"","@z":"51","@statebuttonuseinternalstates":"","@textfont":"PregameButtons","@textfontsize":"18","@textcolor":"255 255 255","@textcenterhoriz":"","@textcentervert":"","@texturecoords":"0 0 0.6328125 1","@mouseovertext":"$$41536$$","@sound":"UI_DefaultPregameClickSet","#text":"Create","command":"gadgetReal(\"UIHCDeckCreateDlg\")","stateentry":[{"@background":"ui\\core_ui\\button_large_normal","#text":""},{"@background":"ui\\core_ui\\button_large_clicked","#text":""},{"@background":"ui\\core_ui\\button_large_high","#text":""},{"@background":"ui\\core_ui\\button_large_disable","#text":""}]},{"@name":"homeCityDeckButtons-DeleteButton","@type":"stateButton","@size1024":"231 732 336 760","@bevelbutton":"","@z":"51","@statebuttonuseinternalstates":"","@textfont":"PregameButtons","@textfontsize":"18","@textcolor":"255 255 255","@textcenterhoriz":"","@textcentervert":"","@texturecoords":"0 0 0.6328125 1","@mouseovertext":"$$41538$$","@sound":"UI_DefaultPregameClickSet","#text":"Delete","stateentry":[{"@background":"ui\\core_ui\\button_large_normal","#text":""},{"@background":"ui\\core_ui\\button_large_clicked","#text":""},{"@background":"ui\\core_ui\\button_large_high","#text":""},{"@background":"ui\\core_ui\\button_large_disable","#text":""}]}]}}}